{
	"Code": "naza",
	"Culture": "naza",
	"Name": "Nazarick",
	"Emblem": "session/portraits/emblems/nazarick_emblem.png",
	"History": "Nazarick is a fictional civilization. They are known as shadow roamers of the world",
	"Music": [
		{
			"File": "Countdown.ogg",
			"Type": "peace"
		},
		{
			"File": "Hero Select.ogg",
			"Type": "peace"
		},
		{
			"File": "Battle 1.ogg",
			"Type": "peace"
		}
	],
	"Factions": [
		{
			"Name": "Nazarick",
			"Description": "N/A",
			"Technologies": [
				{
					"Name":"Thingstead",
					"History":"The thing was the assembly of the free men. At the thing, disputes were resolved and political decisions were made.",
					"Description":"Units +5 Health, unlocks Hero units."
				}
			],
			"Heroes": [
				{
					"Name": "Razor the Lightning",
					"Class": "",
					"Armament": "",
					"Emblem": "",
					"History": "With Razor, the Nazarick get the edge."
				}
			]
		}
	],
	"CivBonuses": [
		{
			"Name": "Grand Magus of Nazarick",
			"History": "Nazarick learned of Celtic structures, which were mostly made of wood with rubble foundations.",
			"Description": "Nazarick buildings have 20% less health, but are also 20% cheaper and faster to construct."
		},
		{
			"Name": "Emperor of Emperors",
			"History": "?",
			"Description": "The Nazarick troops produce a surprisingly large number soldiers. Their capabilities remain a secret to the rest of the world."
		}
	],
	"TeamBonuses": [],
	"Structures": [],
	"WallSets": [],
	"StartEntities": [
		{
			"Template": "structures/naza_civil_centre"
		},
		{
			"Template": "units/naza_support_female_citizen",
			"Count": 4
		},
		{
			"Template": "units/naza_infantry_spearman_b",
			"Count": 2
		},
		{
			"Template": "units/naza_infantry_javelinist_b",
			"Count": 2
		}
	],
	"Formations": [
		"special/formations/null",
		"special/formations/box",
		"special/formations/column_closed",
		"special/formations/line_closed",
		"special/formations/column_open",
		"special/formations/line_open",
		"special/formations/flank",
		"special/formations/skirmish",
		"special/formations/wedge",
		"special/formations/battle_line",
		"special/formations/phalanx"
	],
	"AINames": [],
	"SkirmishReplacements": {},
	"SelectableInGameSetup": true
}